{"columns":[{"field":"lista","title":"Listas"},{"field":"sigla_lista","title":"Sigla Listas"},{"field":"NQN mesa 1","title":"NQN mesa 1"},{"field":"SMA mesa 1","title":"SMA mesa 1"},{"field":"total","title":"Total"}],"data":[{"lista":"LISTA N\u00ba 6 \"Alameda Estudiantes de Turismo\"","sigla_lista":"L6 ALET","NQN mesa 1":197,"SMA mesa 1":17,"total":214}],"labels":["L6 ALET   ","L6 ALET   "],"total":[214,214],"fecha":"17\/05\/2018 11:03:44","titulo":"Votos FATU Consejero Directivo Estudiantes ","columns2":[{"field":"lista","title":"Listas"},{"field":"escanos","title":"Esca\u00f1os"},{"field":1,"title":1},{"field":2,"title":2}],"data2":[{"lista":"L6 ALET   ","escanos":2,"1":"(2)214","2":"(4)107","3":71,"4":53},{"lista":"L6 ALET   ","escanos":2,"1":"(2)214","2":"(4)107","3":71,"4":53}]}