{"columns":[{"field":"lista","title":"Listas"},{"field":"sigla_lista","title":"Sigla Listas"},{"field":"CSA mesa 1","title":"CSA mesa 1"},{"field":"SMA mesa 1","title":"SMA mesa 1"},{"field":"total","title":"Total"}],"data":[{"lista":"LISTA N\u00ba26:  \"JUNTOS POR AGRARIAS\"","sigla_lista":"L26 JPAG","CSA mesa 1":22,"SMA mesa 1":40,"total":62},{"lista":"LISTA N\u00ba 27: \"ECU AGRARIAS\"","sigla_lista":"L27 ECUA","CSA mesa 1":102,"SMA mesa 1":7,"total":109}],"labels":["L26 JPAG  ","L26 JPAG  ","L27 ECUA  ","L27 ECUA  "],"total":[62,62,109,109],"fecha":"17\/05\/2018 11:03:44","titulo":"Votos FACA Decano Estudiantes "}