{"columns":[{"field":"lista","title":"Listas"},{"field":"sigla_lista","title":"Sigla Listas"},{"field":"CSA mesa 1","title":"CSA mesa 1"},{"field":"SMA mesa 1","title":"SMA mesa 1"},{"field":"total","title":"Total"}],"data":[{"lista":"LISTA N\u00ba26:  \"JUNTOS POR AGRARIAS\"","sigla_lista":"L26 JPAG","CSA mesa 1":49,"SMA mesa 1":35,"total":84},{"lista":"LISTA N\u00ba 27: \"ECU AGRARIAS\"","sigla_lista":"L27 ECUA","CSA mesa 1":1,"SMA mesa 1":3,"total":4}],"labels":["L26 JPAG  ","L26 JPAG  ","L27 ECUA  ","L27 ECUA  "],"total":[84,84,4,4],"fecha":"17\/05\/2018 11:03:44","titulo":"Votos FACA Decano Docente     "}